websocket.cp39-win_amd64.pyd
discord.pyx-0.0.0.dist-info/METADATA
discord.pyx-0.0.0.dist-info/WHEEL
discord.pyx-0.0.0.dist-info/top_level.txt
discord.pyx-0.0.0.dist-info/RECORD
